LICENSE
MANIFEST.in
README.rst
setup.cfg
setup.py
docs/Makefile
docs/conf.py
docs/credits.rst
docs/gui.rst
docs/index.rst
docs/installation.rst
docs/list_of_functions.rst
docs/make.bat
docs/requirements.txt
docs/test.rst
docs/using.rst
docs/_static/ccp4console.gif
docs/_static/example_CCfree.png
docs/_static/example_R-values.png
docs/_static/phenix_command_prompt.gif
pairef/__init__.py
pairef/__main__.py
pairef/commons.py
pairef/graphs.py
pairef/gui.py
pairef/launcher.py
pairef/preparation.py
pairef/refinement.py
pairef/settings.py
pairef.egg-info/PKG-INFO
pairef.egg-info/SOURCES.txt
pairef.egg-info/dependency_links.txt
pairef.egg-info/entry_points.txt
pairef.egg-info/not-zip-safe
pairef.egg-info/requires.txt
pairef.egg-info/top_level.txt
pairef/static/pairef_logo_64.png
pairef/static/styles.css
test/helper.py
test/helper.pyc
test/test_commons.py
test/test_graphs.py
test/test_initial.py
test/test_integration_long.py
test/test_integration_quick.py
test/fixtures/A_R-values.csv
test/fixtures/NK_R00_1-50A.csv
test/fixtures/NK_R00_1-60A.csv
test/fixtures/NK_R00_1-70A.csv
test/fixtures/NK_R00_1-80A.csv
test/fixtures/NK_Rgap.csv
test/fixtures/lysozyme_1-40A.log
test/fixtures/mdm2_1-60A.pdb
test/fixtures/mdm2_merged.mtz