Metadata-Version: 1.1
Name: pairef
Version: 1.4.3
Summary: Automatic PAIRed REFinement protocol
Home-page: https://pairef.fjfi.cvut.cz/
Author: Martin Maly
Author-email: martin.maly@fjfi.cvut.cz
License: GNU Lesser General Public License v3 (LGPLv3)
Keywords: macromolecular crystallography,research
Platform: UNKNOWN
Classifier: Environment :: Console
Classifier: Environment :: Web Environment
Classifier: Intended Audience :: Science/Research
Classifier: License :: OSI Approved :: GNU Lesser General Public License v3 (LGPLv3)
Classifier: Natural Language :: English
Classifier: Operating System :: POSIX :: Linux
Classifier: Operating System :: Microsoft :: Windows
Classifier: Operating System :: MacOS
Classifier: Programming Language :: Python
Classifier: Programming Language :: Python :: 2
Classifier: Programming Language :: Python :: 2.7
Classifier: Programming Language :: Python :: 3
Classifier: Programming Language :: Python :: 3.7
Classifier: Topic :: Scientific/Engineering :: Bio-Informatics
Classifier: Topic :: Scientific/Engineering :: Physics
